{
  "iteration": 1,
  "results_dataframe": [
    {
      "dataset": "boiler",
      "missing_data_type": "MCAR",
      "missing_rate": 2,
      "iteration_nr": 2,
      "fixing_method": "gaf-unet",
      "prediction_method": "XGBoost",
      "MAPE": 6.889436219243664,
      "MAE": 36.90940856933594,
      "RMSE": 54.98526270330363
    },
    {
      "dataset": "boiler",
      "missing_data_type": "MCAR",
      "missing_rate": 2,
      "iteration_nr": 2,
      "fixing_method": "impute_mean",
      "prediction_method": "XGBoost",
      "MAPE": 0.05906626683212866,
      "MAE": 0.3164829101562418,
      "RMSE": 0.3229844147288726
    },
    {
      "dataset": "boiler",
      "missing_data_type": "MCAR",
      "missing_rate": 2,
      "iteration_nr": 2,
      "fixing_method": "impute_median",
      "prediction_method": "XGBoost",
      "MAPE": 0.05408851754212749,
      "MAE": 0.2898105468749918,
      "RMSE": 0.29575960989983685
    },
    {
      "dataset": "boiler",
      "missing_data_type": "MCAR",
      "missing_rate": 2,
      "iteration_nr": 2,
      "fixing_method": "impute_mode",
      "prediction_method": "XGBoost",
      "MAPE": 0.0524369747078015,
      "MAE": 0.2809604492187418,
      "RMSE": 0.2852050077689336
    },
    {
      "dataset": "boiler",
      "missing_data_type": "MCAR",
      "missing_rate": 2,
      "iteration_nr": 2,
      "fixing_method": "impute_ffill",
      "prediction_method": "XGBoost",
      "MAPE": 0.04877665803089253,
      "MAE": 0.2613498535156168,
      "RMSE": 0.2668095169255781
    },
    {
      "dataset": "boiler",
      "missing_data_type": "MCAR",
      "missing_rate": 2,
      "iteration_nr": 2,
      "fixing_method": "impute_bfill",
      "prediction_method": "XGBoost",
      "MAPE": 0.04961539771301451,
      "MAE": 0.2658420410156168,
      "RMSE": 0.2710659235928683
    },
    {
      "dataset": "boiler",
      "missing_data_type": "MCAR",
      "missing_rate": 2,
      "iteration_nr": 2,
      "fixing_method": "interpolate_nearest",
      "prediction_method": "XGBoost",
      "MAPE": 0.04877999948090905,
      "MAE": 0.2613681640624918,
      "RMSE": 0.2662655957673383
    },
    {
      "dataset": "boiler",
      "missing_data_type": "MCAR",
      "missing_rate": 2,
      "iteration_nr": 2,
      "fixing_method": "interpolate_linear",
      "prediction_method": "XGBoost",
      "MAPE": 0.04900325749150072,
      "MAE": 0.2625644531249918,
      "RMSE": 0.26785031497926415
    },
    {
      "dataset": "boiler",
      "missing_data_type": "MCAR",
      "missing_rate": 2,
      "iteration_nr": 2,
      "fixing_method": "interpolate_index",
      "prediction_method": "XGBoost",
      "MAPE": 0.04900325749150072,
      "MAE": 0.2625644531249918,
      "RMSE": 0.26785031497926415
    },
    {
      "dataset": "boiler",
      "missing_data_type": "MCAR",
      "missing_rate": 2,
      "iteration_nr": 2,
      "fixing_method": "interpolate_quadratic",
      "prediction_method": "XGBoost",
      "MAPE": 0.048035399411507404,
      "MAE": 0.2573764648437418,
      "RMSE": 0.26359675259284404
    },
    {
      "dataset": "boiler",
      "missing_data_type": "MCAR",
      "missing_rate": 2,
      "iteration_nr": 2,
      "fixing_method": "interpolate_cubic",
      "prediction_method": "XGBoost",
      "MAPE": 0.04864115709677158,
      "MAE": 0.2606235351562418,
      "RMSE": 0.26694877156544244
    },
    {
      "dataset": "boiler",
      "missing_data_type": "MCAR",
      "missing_rate": 2,
      "iteration_nr": 2,
      "fixing_method": "interpolate_polynomial",
      "prediction_method": "XGBoost",
      "MAPE": 0.048035399411507404,
      "MAE": 0.2573764648437418,
      "RMSE": 0.26359675259284404
    },
    {
      "dataset": "boiler",
      "missing_data_type": "MCAR",
      "missing_rate": 2,
      "iteration_nr": 2,
      "fixing_method": "interpolate_pchip",
      "prediction_method": "XGBoost",
      "MAPE": 0.048450863667626375,
      "MAE": 0.2596042480468668,
      "RMSE": 0.2648660873681847
    },
    {
      "dataset": "boiler",
      "missing_data_type": "MCAR",
      "missing_rate": 2,
      "iteration_nr": 2,
      "fixing_method": "interpolate_akima",
      "prediction_method": "XGBoost",
      "MAPE": 0.0472309462711518,
      "MAE": 0.2530673828124918,
      "RMSE": 0.2594417867735952
    },
    {
      "dataset": "pump",
      "missing_data_type": "MCAR",
      "missing_rate": 2,
      "iteration_nr": 2,
      "fixing_method": "gaf-unet",
      "prediction_method": "XGBoost",
      "MAPE": 3.884550714943481,
      "MAE": 30.942894716796864,
      "RMSE": 43.58298709642947
    },
    {
      "dataset": "pump",
      "missing_data_type": "MCAR",
      "missing_rate": 2,
      "iteration_nr": 2,
      "fixing_method": "impute_mean",
      "prediction_method": "XGBoost",
      "MAPE": 1.3871580520442577,
      "MAE": 10.961354716796894,
      "RMSE": 15.866632106554235
    },
    {
      "dataset": "pump",
      "missing_data_type": "MCAR",
      "missing_rate": 2,
      "iteration_nr": 2,
      "fixing_method": "impute_median",
      "prediction_method": "XGBoost",
      "MAPE": 1.1197665408414683,
      "MAE": 8.864998515625018,
      "RMSE": 10.532298979992293
    },
    {
      "dataset": "pump",
      "missing_data_type": "MCAR",
      "missing_rate": 2,
      "iteration_nr": 2,
      "fixing_method": "impute_mode",
      "prediction_method": "XGBoost",
      "MAPE": 1.4993448308843356,
      "MAE": 11.873710576171892,
      "RMSE": 14.225066445339131
    },
    {
      "dataset": "pump",
      "missing_data_type": "MCAR",
      "missing_rate": 2,
      "iteration_nr": 2,
      "fixing_method": "impute_ffill",
      "prediction_method": "XGBoost",
      "MAPE": 0.9846687918215727,
      "MAE": 7.783897343750016,
      "RMSE": 10.690490163606562
    },
    {
      "dataset": "pump",
      "missing_data_type": "MCAR",
      "missing_rate": 2,
      "iteration_nr": 2,
      "fixing_method": "impute_bfill",
      "prediction_method": "XGBoost",
      "MAPE": 0.8122842806384425,
      "MAE": 6.415798076171893,
      "RMSE": 9.222655710006212
    },
    {
      "dataset": "pump",
      "missing_data_type": "MCAR",
      "missing_rate": 2,
      "iteration_nr": 2,
      "fixing_method": "interpolate_nearest",
      "prediction_method": "XGBoost",
      "MAPE": 1.04576559101883,
      "MAE": 8.270225468750017,
      "RMSE": 11.099845984687501
    },
    {
      "dataset": "pump",
      "missing_data_type": "MCAR",
      "missing_rate": 2,
      "iteration_nr": 2,
      "fixing_method": "interpolate_linear",
      "prediction_method": "XGBoost",
      "MAPE": 0.9229552013145619,
      "MAE": 7.2951095019531405,
      "RMSE": 9.889087308729325
    },
    {
      "dataset": "pump",
      "missing_data_type": "MCAR",
      "missing_rate": 2,
      "iteration_nr": 2,
      "fixing_method": "interpolate_index",
      "prediction_method": "XGBoost",
      "MAPE": 0.9229552013145619,
      "MAE": 7.2951095019531405,
      "RMSE": 9.889087308729325
    },
    {
      "dataset": "pump",
      "missing_data_type": "MCAR",
      "missing_rate": 2,
      "iteration_nr": 2,
      "fixing_method": "interpolate_quadratic",
      "prediction_method": "XGBoost",
      "MAPE": 0.8849973705117467,
      "MAE": 6.993713701171885,
      "RMSE": 9.792287626812096
    },
    {
      "dataset": "pump",
      "missing_data_type": "MCAR",
      "missing_rate": 2,
      "iteration_nr": 2,
      "fixing_method": "interpolate_cubic",
      "prediction_method": "XGBoost",
      "MAPE": 0.9079914554274384,
      "MAE": 7.179435673828141,
      "RMSE": 9.675641873829077
    },
    {
      "dataset": "pump",
      "missing_data_type": "MCAR",
      "missing_rate": 2,
      "iteration_nr": 2,
      "fixing_method": "interpolate_polynomial",
      "prediction_method": "XGBoost",
      "MAPE": 0.8849973705117467,
      "MAE": 6.993713701171885,
      "RMSE": 9.792287626812096
    },
    {
      "dataset": "pump",
      "missing_data_type": "MCAR",
      "missing_rate": 2,
      "iteration_nr": 2,
      "fixing_method": "interpolate_pchip",
      "prediction_method": "XGBoost",
      "MAPE": 0.8826767270153867,
      "MAE": 6.974864140625016,
      "RMSE": 9.783542943809852
    },
    {
      "dataset": "pump",
      "missing_data_type": "MCAR",
      "missing_rate": 2,
      "iteration_nr": 2,
      "fixing_method": "interpolate_akima",
      "prediction_method": "XGBoost",
      "MAPE": 0.88705533284435,
      "MAE": 7.00952791015626,
      "RMSE": 9.722119581377425
    },
    {
      "dataset": "vibr",
      "missing_data_type": "MCAR",
      "missing_rate": 2,
      "iteration_nr": 2,
      "fixing_method": "gaf-unet",
      "prediction_method": "XGBoost",
      "MAPE": 27.959649757274562,
      "MAE": 9.697827441999031,
      "RMSE": 10.869850305057827
    },
    {
      "dataset": "vibr",
      "missing_data_type": "MCAR",
      "missing_rate": 2,
      "iteration_nr": 2,
      "fixing_method": "impute_mean",
      "prediction_method": "XGBoost",
      "MAPE": 24.278731493094067,
      "MAE": 8.160438804112392,
      "RMSE": 9.415012516331569
    },
    {
      "dataset": "vibr",
      "missing_data_type": "MCAR",
      "missing_rate": 2,
      "iteration_nr": 2,
      "fixing_method": "impute_median",
      "prediction_method": "XGBoost",
      "MAPE": 23.881323327560615,
      "MAE": 8.181156234227139,
      "RMSE": 9.356735112982593
    },
    {
      "dataset": "vibr",
      "missing_data_type": "MCAR",
      "missing_rate": 2,
      "iteration_nr": 2,
      "fixing_method": "impute_mode",
      "prediction_method": "XGBoost",
      "MAPE": 30.138724284514538,
      "MAE": 10.031731109105069,
      "RMSE": 10.80302208163318
    },
    {
      "dataset": "vibr",
      "missing_data_type": "MCAR",
      "missing_rate": 2,
      "iteration_nr": 2,
      "fixing_method": "impute_ffill",
      "prediction_method": "XGBoost",
      "MAPE": 24.17893308397028,
      "MAE": 8.223061446629483,
      "RMSE": 9.281375689560717
    },
    {
      "dataset": "vibr",
      "missing_data_type": "MCAR",
      "missing_rate": 2,
      "iteration_nr": 2,
      "fixing_method": "impute_bfill",
      "prediction_method": "XGBoost",
      "MAPE": 28.809204583352887,
      "MAE": 9.768813590489346,
      "RMSE": 10.558124950925682
    },
    {
      "dataset": "vibr",
      "missing_data_type": "MCAR",
      "missing_rate": 2,
      "iteration_nr": 2,
      "fixing_method": "interpolate_nearest",
      "prediction_method": "XGBoost",
      "MAPE": 24.17893308397028,
      "MAE": 8.223061446629483,
      "RMSE": 9.281375689560717
    },
    {
      "dataset": "vibr",
      "missing_data_type": "MCAR",
      "missing_rate": 2,
      "iteration_nr": 2,
      "fixing_method": "interpolate_linear",
      "prediction_method": "XGBoost",
      "MAPE": 27.58143879090448,
      "MAE": 9.390312461338954,
      "RMSE": 11.240542631281572
    },
    {
      "dataset": "vibr",
      "missing_data_type": "MCAR",
      "missing_rate": 2,
      "iteration_nr": 2,
      "fixing_method": "interpolate_index",
      "prediction_method": "XGBoost",
      "MAPE": 27.58143879090448,
      "MAE": 9.390312461338954,
      "RMSE": 11.240542631281572
    },
    {
      "dataset": "vibr",
      "missing_data_type": "MCAR",
      "missing_rate": 2,
      "iteration_nr": 2,
      "fixing_method": "interpolate_quadratic",
      "prediction_method": "XGBoost",
      "MAPE": 20.609162580233647,
      "MAE": 6.7499692664327045,
      "RMSE": 8.444308398344742
    },
    {
      "dataset": "vibr",
      "missing_data_type": "MCAR",
      "missing_rate": 2,
      "iteration_nr": 2,
      "fixing_method": "interpolate_cubic",
      "prediction_method": "XGBoost",
      "MAPE": 29.085309728612017,
      "MAE": 9.524449614964443,
      "RMSE": 10.190155924671094
    },
    {
      "dataset": "vibr",
      "missing_data_type": "MCAR",
      "missing_rate": 2,
      "iteration_nr": 2,
      "fixing_method": "interpolate_polynomial",
      "prediction_method": "XGBoost",
      "MAPE": 20.609162580233647,
      "MAE": 6.7499692664327045,
      "RMSE": 8.444308398344742
    },
    {
      "dataset": "vibr",
      "missing_data_type": "MCAR",
      "missing_rate": 2,
      "iteration_nr": 2,
      "fixing_method": "interpolate_pchip",
      "prediction_method": "XGBoost",
      "MAPE": 25.21103334085114,
      "MAE": 8.539454998597519,
      "RMSE": 10.294610573398119
    },
    {
      "dataset": "vibr",
      "missing_data_type": "MCAR",
      "missing_rate": 2,
      "iteration_nr": 2,
      "fixing_method": "interpolate_akima",
      "prediction_method": "XGBoost",
      "MAPE": 22.227176137142973,
      "MAE": 7.862332209269878,
      "RMSE": 8.936946502153816
    }
  ],
  "metrics": {
    "dataset_0_MCAR_2p_gaf-unet_XGBoost": {
      "MAE": 36.90940856933594,
      "RMSE": 54.98526270330363,
      "MAPE": 6.889436219243664
    },
    "dataset_0_MCAR_2p_impute_mean_XGBoost": {
      "MAE": 0.3164829101562418,
      "RMSE": 0.3229844147288726,
      "MAPE": 0.05906626683212866
    },
    "dataset_0_MCAR_2p_impute_median_XGBoost": {
      "MAE": 0.2898105468749918,
      "RMSE": 0.29575960989983685,
      "MAPE": 0.05408851754212749
    },
    "dataset_0_MCAR_2p_impute_mode_XGBoost": {
      "MAE": 0.2809604492187418,
      "RMSE": 0.2852050077689336,
      "MAPE": 0.0524369747078015
    },
    "dataset_0_MCAR_2p_impute_ffill_XGBoost": {
      "MAE": 0.2613498535156168,
      "RMSE": 0.2668095169255781,
      "MAPE": 0.04877665803089253
    },
    "dataset_0_MCAR_2p_impute_bfill_XGBoost": {
      "MAE": 0.2658420410156168,
      "RMSE": 0.2710659235928683,
      "MAPE": 0.04961539771301451
    },
    "dataset_0_MCAR_2p_interpolate_nearest_XGBoost": {
      "MAE": 0.2613681640624918,
      "RMSE": 0.2662655957673383,
      "MAPE": 0.04877999948090905
    },
    "dataset_0_MCAR_2p_interpolate_linear_XGBoost": {
      "MAE": 0.2625644531249918,
      "RMSE": 0.26785031497926415,
      "MAPE": 0.04900325749150072
    },
    "dataset_0_MCAR_2p_interpolate_index_XGBoost": {
      "MAE": 0.2625644531249918,
      "RMSE": 0.26785031497926415,
      "MAPE": 0.04900325749150072
    },
    "dataset_0_MCAR_2p_interpolate_quadratic_XGBoost": {
      "MAE": 0.2573764648437418,
      "RMSE": 0.26359675259284404,
      "MAPE": 0.048035399411507404
    },
    "dataset_0_MCAR_2p_interpolate_cubic_XGBoost": {
      "MAE": 0.2606235351562418,
      "RMSE": 0.26694877156544244,
      "MAPE": 0.04864115709677158
    },
    "dataset_0_MCAR_2p_interpolate_polynomial_XGBoost": {
      "MAE": 0.2573764648437418,
      "RMSE": 0.26359675259284404,
      "MAPE": 0.048035399411507404
    },
    "dataset_0_MCAR_2p_interpolate_pchip_XGBoost": {
      "MAE": 0.2596042480468668,
      "RMSE": 0.2648660873681847,
      "MAPE": 0.048450863667626375
    },
    "dataset_0_MCAR_2p_interpolate_akima_XGBoost": {
      "MAE": 0.2530673828124918,
      "RMSE": 0.2594417867735952,
      "MAPE": 0.0472309462711518
    },
    "dataset_1_MCAR_2p_gaf-unet_XGBoost": {
      "MAE": 30.942894716796864,
      "RMSE": 43.58298709642947,
      "MAPE": 3.884550714943481
    },
    "dataset_1_MCAR_2p_impute_mean_XGBoost": {
      "MAE": 10.961354716796894,
      "RMSE": 15.866632106554235,
      "MAPE": 1.3871580520442577
    },
    "dataset_1_MCAR_2p_impute_median_XGBoost": {
      "MAE": 8.864998515625018,
      "RMSE": 10.532298979992293,
      "MAPE": 1.1197665408414683
    },
    "dataset_1_MCAR_2p_impute_mode_XGBoost": {
      "MAE": 11.873710576171892,
      "RMSE": 14.225066445339131,
      "MAPE": 1.4993448308843356
    },
    "dataset_1_MCAR_2p_impute_ffill_XGBoost": {
      "MAE": 7.783897343750016,
      "RMSE": 10.690490163606562,
      "MAPE": 0.9846687918215727
    },
    "dataset_1_MCAR_2p_impute_bfill_XGBoost": {
      "MAE": 6.415798076171893,
      "RMSE": 9.222655710006212,
      "MAPE": 0.8122842806384425
    },
    "dataset_1_MCAR_2p_interpolate_nearest_XGBoost": {
      "MAE": 8.270225468750017,
      "RMSE": 11.099845984687501,
      "MAPE": 1.04576559101883
    },
    "dataset_1_MCAR_2p_interpolate_linear_XGBoost": {
      "MAE": 7.2951095019531405,
      "RMSE": 9.889087308729325,
      "MAPE": 0.9229552013145619
    },
    "dataset_1_MCAR_2p_interpolate_index_XGBoost": {
      "MAE": 7.2951095019531405,
      "RMSE": 9.889087308729325,
      "MAPE": 0.9229552013145619
    },
    "dataset_1_MCAR_2p_interpolate_quadratic_XGBoost": {
      "MAE": 6.993713701171885,
      "RMSE": 9.792287626812096,
      "MAPE": 0.8849973705117467
    },
    "dataset_1_MCAR_2p_interpolate_cubic_XGBoost": {
      "MAE": 7.179435673828141,
      "RMSE": 9.675641873829077,
      "MAPE": 0.9079914554274384
    },
    "dataset_1_MCAR_2p_interpolate_polynomial_XGBoost": {
      "MAE": 6.993713701171885,
      "RMSE": 9.792287626812096,
      "MAPE": 0.8849973705117467
    },
    "dataset_1_MCAR_2p_interpolate_pchip_XGBoost": {
      "MAE": 6.974864140625016,
      "RMSE": 9.783542943809852,
      "MAPE": 0.8826767270153867
    },
    "dataset_1_MCAR_2p_interpolate_akima_XGBoost": {
      "MAE": 7.00952791015626,
      "RMSE": 9.722119581377425,
      "MAPE": 0.88705533284435
    },
    "dataset_2_MCAR_2p_gaf-unet_XGBoost": {
      "MAE": 9.697827441999031,
      "RMSE": 10.869850305057827,
      "MAPE": 27.959649757274562
    },
    "dataset_2_MCAR_2p_impute_mean_XGBoost": {
      "MAE": 8.160438804112392,
      "RMSE": 9.415012516331569,
      "MAPE": 24.278731493094067
    },
    "dataset_2_MCAR_2p_impute_median_XGBoost": {
      "MAE": 8.181156234227139,
      "RMSE": 9.356735112982593,
      "MAPE": 23.881323327560615
    },
    "dataset_2_MCAR_2p_impute_mode_XGBoost": {
      "MAE": 10.031731109105069,
      "RMSE": 10.80302208163318,
      "MAPE": 30.138724284514538
    },
    "dataset_2_MCAR_2p_impute_ffill_XGBoost": {
      "MAE": 8.223061446629483,
      "RMSE": 9.281375689560717,
      "MAPE": 24.17893308397028
    },
    "dataset_2_MCAR_2p_impute_bfill_XGBoost": {
      "MAE": 9.768813590489346,
      "RMSE": 10.558124950925682,
      "MAPE": 28.809204583352887
    },
    "dataset_2_MCAR_2p_interpolate_nearest_XGBoost": {
      "MAE": 8.223061446629483,
      "RMSE": 9.281375689560717,
      "MAPE": 24.17893308397028
    },
    "dataset_2_MCAR_2p_interpolate_linear_XGBoost": {
      "MAE": 9.390312461338954,
      "RMSE": 11.240542631281572,
      "MAPE": 27.58143879090448
    },
    "dataset_2_MCAR_2p_interpolate_index_XGBoost": {
      "MAE": 9.390312461338954,
      "RMSE": 11.240542631281572,
      "MAPE": 27.58143879090448
    },
    "dataset_2_MCAR_2p_interpolate_quadratic_XGBoost": {
      "MAE": 6.7499692664327045,
      "RMSE": 8.444308398344742,
      "MAPE": 20.609162580233647
    },
    "dataset_2_MCAR_2p_interpolate_cubic_XGBoost": {
      "MAE": 9.524449614964443,
      "RMSE": 10.190155924671094,
      "MAPE": 29.085309728612017
    },
    "dataset_2_MCAR_2p_interpolate_polynomial_XGBoost": {
      "MAE": 6.7499692664327045,
      "RMSE": 8.444308398344742,
      "MAPE": 20.609162580233647
    },
    "dataset_2_MCAR_2p_interpolate_pchip_XGBoost": {
      "MAE": 8.539454998597519,
      "RMSE": 10.294610573398119,
      "MAPE": 25.21103334085114
    },
    "dataset_2_MCAR_2p_interpolate_akima_XGBoost": {
      "MAE": 7.862332209269878,
      "RMSE": 8.936946502153816,
      "MAPE": 22.227176137142973
    }
  },
  "predictions": {
    "dataset_0_MCAR_2p_gaf-unet_XGBoost": [
      523.4502563476562,
      534.4171752929688,
      531.256103515625,
      534.4776000976562,
      537.6534423828125,
      485.2862854003906,
      516.0697631835938,
      457.8152160644531,
      460.7740783691406,
      411.51287841796875
    ],
    "dataset_0_MCAR_2p_impute_mean_XGBoost": [
      536.2481689453125,
      536.2776489257812,
      536.1486206054688,
      536.1483764648438,
      536.1483764648438,
      536.06201171875,
      536.1460571289062,
      536.0669555664062,
      535.9541015625,
      536.12451171875
    ],
    "dataset_0_MCAR_2p_impute_median_XGBoost": [
      536.2260131835938,
      536.2056274414062,
      536.1246337890625,
      536.1246337890625,
      536.1246337890625,
      536.054443359375,
      536.1289672851562,
      536.034912109375,
      535.9397583007812,
      536.094482421875
    ],
    "dataset_0_MCAR_2p_impute_mode_XGBoost": [
      536.1944580078125,
      536.1950073242188,
      536.128662109375,
      536.1011352539062,
      536.1011352539062,
      536.0535888671875,
      536.1034545898438,
      536.0575561523438,
      535.967529296875,
      536.0670776367188
    ],
    "dataset_0_MCAR_2p_impute_ffill_XGBoost": [
      536.23583984375,
      536.2015380859375,
      536.1019897460938,
      536.060302734375,
      536.059814453125,
      536.028076171875,
      536.0623779296875,
      536.0293579101562,
      535.935546875,
      536.0586547851562
    ],
    "dataset_0_MCAR_2p_impute_bfill_XGBoost": [
      536.2132568359375,
      536.1807250976562,
      536.1072387695312,
      536.0711059570312,
      536.0711059570312,
      536.0245361328125,
      536.0711059570312,
      536.0453491210938,
      535.968017578125,
      536.0659790039062
    ],
    "dataset_0_MCAR_2p_interpolate_nearest_XGBoost": [
      536.2360229492188,
      536.201171875,
      536.1056518554688,
      536.0628051757812,
      536.064453125,
      536.0327758789062,
      536.064453125,
      536.0233154296875,
      535.9322509765625,
      536.05078125
    ],
    "dataset_0_MCAR_2p_interpolate_linear_XGBoost": [
      536.2364501953125,
      536.2030639648438,
      536.0966796875,
      536.0642700195312,
      536.0663452148438,
      536.0341796875,
      536.0877075195312,
      536.02978515625,
      535.9222412109375,
      536.044921875
    ],
    "dataset_0_MCAR_2p_interpolate_index_XGBoost": [
      536.2364501953125,
      536.2030639648438,
      536.0966796875,
      536.0642700195312,
      536.0663452148438,
      536.0341796875,
      536.0877075195312,
      536.02978515625,
      535.9222412109375,
      536.044921875
    ],
    "dataset_0_MCAR_2p_interpolate_quadratic_XGBoost": [
      536.2107543945312,
      536.188232421875,
      536.0794067382812,
      536.0569458007812,
      536.0682373046875,
      536.0313110351562,
      536.0565795898438,
      536.0298461914062,
      535.9423828125,
      536.070068359375
    ],
    "dataset_0_MCAR_2p_interpolate_cubic_XGBoost": [
      536.2283935546875,
      536.2085571289062,
      536.093017578125,
      536.046875,
      536.0753784179688,
      536.029296875,
      536.0571899414062,
      536.030517578125,
      535.9273681640625,
      536.0696411132812
    ],
    "dataset_0_MCAR_2p_interpolate_polynomial_XGBoost": [
      536.2107543945312,
      536.188232421875,
      536.0794067382812,
      536.0569458007812,
      536.0682373046875,
      536.0313110351562,
      536.0565795898438,
      536.0298461914062,
      535.9423828125,
      536.070068359375
    ],
    "dataset_0_MCAR_2p_interpolate_pchip_XGBoost": [
      536.2262573242188,
      536.1998901367188,
      536.099365234375,
      536.0481567382812,
      536.06689453125,
      536.0397338867188,
      536.0657958984375,
      536.0333251953125,
      535.9229736328125,
      536.0536499023438
    ],
    "dataset_0_MCAR_2p_interpolate_akima_XGBoost": [
      536.2216186523438,
      536.2003784179688,
      536.0829467773438,
      536.0440673828125,
      536.05322265625,
      536.0250244140625,
      536.0682373046875,
      536.0181884765625,
      535.922607421875,
      536.0543823242188
    ],
    "dataset_1_MCAR_2p_gaf-unet_XGBoost": [
      798.4790649414062,
      786.6249389648438,
      776.7733154296875,
      782.9801635742188,
      709.4232788085938,
      792.4329223632812,
      718.216796875,
      806.5946044921875,
      783.146240234375,
      734.077880859375
    ],
    "dataset_1_MCAR_2p_impute_mean_XGBoost": [
      799.9122314453125,
      801.1341552734375,
      802.8115234375,
      800.4703369140625,
      801.1341552734375,
      819.3779907226562,
      821.478271484375,
      795.384033203125,
      801.1341552734375,
      802.8115234375
    ],
    "dataset_1_MCAR_2p_impute_median_XGBoost": [
      802.8245239257812,
      803.0241088867188,
      805.7763671875,
      802.6893920898438,
      805.8134765625,
      800.9284057617188,
      807.4061889648438,
      798.1721801757812,
      802.7603759765625,
      806.690673828125
    ],
    "dataset_1_MCAR_2p_impute_mode_XGBoost": [
      801.2664184570312,
      804.2552490234375,
      806.1644287109375,
      806.2229614257812,
      805.09130859375,
      809.1619873046875,
      818.7564697265625,
      802.3953857421875,
      805.5473022460938,
      806.4747314453125
    ],
    "dataset_1_MCAR_2p_impute_ffill_XGBoost": [
      799.7241821289062,
      799.494384765625,
      800.9661865234375,
      800.10791015625,
      802.3146362304688,
      806.2203979492188,
      810.1179809570312,
      801.4750366210938,
      799.6472778320312,
      801.28564453125
    ],
    "dataset_1_MCAR_2p_impute_bfill_XGBoost": [
      799.66943359375,
      798.2440185546875,
      801.2489624023438,
      799.9432373046875,
      800.6447143554688,
      803.5797119140625,
      803.1691284179688,
      798.0462036132812,
      799.2662353515625,
      801.2199096679688
    ],
    "dataset_1_MCAR_2p_interpolate_nearest_XGBoost": [
      799.8206176757812,
      799.6748657226562,
      801.03759765625,
      800.0678100585938,
      802.7957763671875,
      806.4977416992188,
      811.8814697265625,
      803.3045654296875,
      800.1900634765625,
      801.1392822265625
    ],
    "dataset_1_MCAR_2p_interpolate_linear_XGBoost": [
      799.8324584960938,
      799.7747192382812,
      802.0806274414062,
      799.8135375976562,
      801.3433837890625,
      804.4326782226562,
      805.8259887695312,
      801.4681396484375,
      799.9970703125,
      802.1137084960938
    ],
    "dataset_1_MCAR_2p_interpolate_index_XGBoost": [
      799.8324584960938,
      799.7747192382812,
      802.0806274414062,
      799.8135375976562,
      801.3433837890625,
      804.4326782226562,
      805.8259887695312,
      801.4681396484375,
      799.9970703125,
      802.1137084960938
    ],
    "dataset_1_MCAR_2p_interpolate_quadratic_XGBoost": [
      799.3189086914062,
      799.336181640625,
      801.2957763671875,
      798.8516235351562,
      800.0108032226562,
      804.4927978515625,
      806.5071411132812,
      801.0282592773438,
      799.7460327148438,
      801.7639770507812
    ],
    "dataset_1_MCAR_2p_interpolate_cubic_XGBoost": [
      799.59375,
      799.1139526367188,
      801.4763793945312,
      799.4521484375,
      801.6480712890625,
      803.0873413085938,
      807.8381958007812,
      800.8502197265625,
      800.0851440429688,
      801.9029541015625
    ],
    "dataset_1_MCAR_2p_interpolate_polynomial_XGBoost": [
      799.3189086914062,
      799.336181640625,
      801.2957763671875,
      798.8516235351562,
      800.0108032226562,
      804.4927978515625,
      806.5071411132812,
      801.0282592773438,
      799.7460327148438,
      801.7639770507812
    ],
    "dataset_1_MCAR_2p_interpolate_pchip_XGBoost": [
      799.7457885742188,
      798.6704711914062,
      801.0302734375,
      799.5943603515625,
      801.8414916992188,
      804.4901733398438,
      806.7109985351562,
      800.8291015625,
      799.0841674804688,
      801.3096923828125
    ],
    "dataset_1_MCAR_2p_interpolate_akima_XGBoost": [
      800.4368286132812,
      800.16259765625,
      800.7071533203125,
      798.8762817382812,
      800.9521484375,
      804.0693969726562,
      807.276123046875,
      800.649658203125,
      800.1246337890625,
      801.5399780273438
    ],
    "dataset_2_MCAR_2p_gaf-unet_XGBoost": [
      45.17459487915039,
      24.049409866333008,
      32.118167877197266,
      35.36708068847656,
      37.0810661315918,
      36.962615966796875,
      41.457088470458984,
      29.88132095336914,
      18.793973922729492,
      30.622461318969727
    ],
    "dataset_2_MCAR_2p_impute_mean_XGBoost": [
      39.983646392822266,
      37.37284851074219,
      28.60231590270996,
      41.562171936035156,
      32.44329833984375,
      34.161468505859375,
      34.603973388671875,
      30.00116539001465,
      36.55514907836914,
      39.84386444091797
    ],
    "dataset_2_MCAR_2p_impute_median_XGBoost": [
      40.23173522949219,
      32.886375427246094,
      30.91206169128418,
      41.577964782714844,
      31.64969825744629,
      34.557071685791016,
      35.56916809082031,
      28.361913681030273,
      35.19898223876953,
      37.46296310424805
    ],
    "dataset_2_MCAR_2p_impute_mode_XGBoost": [
      43.53852844238281,
      39.58904266357422,
      26.78011131286621,
      39.60072708129883,
      36.34718322753906,
      39.32838821411133,
      40.01056671142578,
      35.66878890991211,
      24.304574966430664,
      29.681516647338867
    ],
    "dataset_2_MCAR_2p_impute_ffill_XGBoost": [
      44.7911376953125,
      38.069801330566406,
      31.6149959564209,
      34.54764175415039,
      31.48590087890625,
      37.841339111328125,
      38.82850646972656,
      35.21726989746094,
      32.963890075683594,
      34.572086334228516
    ],
    "dataset_2_MCAR_2p_impute_bfill_XGBoost": [
      40.81654739379883,
      42.102149963378906,
      29.714567184448242,
      39.967979431152344,
      30.958019256591797,
      34.337825775146484,
      36.04751205444336,
      29.22658348083496,
      31.381099700927734,
      35.31696701049805
    ],
    "dataset_2_MCAR_2p_interpolate_nearest_XGBoost": [
      44.7911376953125,
      38.069801330566406,
      31.6149959564209,
      34.54764175415039,
      31.48590087890625,
      37.841339111328125,
      38.82850646972656,
      35.21726989746094,
      32.963890075683594,
      34.572086334228516
    ],
    "dataset_2_MCAR_2p_interpolate_linear_XGBoost": [
      41.81815719604492,
      35.45542526245117,
      31.908964157104492,
      43.05772018432617,
      26.634199142456055,
      33.89759826660156,
      39.71281433105469,
      32.21327209472656,
      37.44789123535156,
      33.72807693481445
    ],
    "dataset_2_MCAR_2p_interpolate_index_XGBoost": [
      41.81815719604492,
      35.45542526245117,
      31.908964157104492,
      43.05772018432617,
      26.634199142456055,
      33.89759826660156,
      39.71281433105469,
      32.21327209472656,
      37.44789123535156,
      33.72807693481445
    ],
    "dataset_2_MCAR_2p_interpolate_quadratic_XGBoost": [
      43.61541748046875,
      28.296628952026367,
      36.49200439453125,
      40.72806167602539,
      34.10555648803711,
      41.78472900390625,
      39.354225158691406,
      29.46767234802246,
      37.356231689453125,
      39.70384979248047
    ],
    "dataset_2_MCAR_2p_interpolate_cubic_XGBoost": [
      43.895450592041016,
      36.22222900390625,
      30.152585983276367,
      40.66825485229492,
      36.88239288330078,
      38.87602615356445,
      42.3835334777832,
      24.560260772705078,
      32.341796875,
      34.80091857910156
    ],
    "dataset_2_MCAR_2p_interpolate_polynomial_XGBoost": [
      43.61541748046875,
      28.296628952026367,
      36.49200439453125,
      40.72806167602539,
      34.10555648803711,
      41.78472900390625,
      39.354225158691406,
      29.46767234802246,
      37.356231689453125,
      39.70384979248047
    ],
    "dataset_2_MCAR_2p_interpolate_pchip_XGBoost": [
      44.81794357299805,
      34.09591293334961,
      33.649044036865234,
      42.6636848449707,
      30.638002395629883,
      32.976993560791016,
      37.1916618347168,
      29.03957748413086,
      38.62208938598633,
      39.69129180908203
    ],
    "dataset_2_MCAR_2p_interpolate_akima_XGBoost": [
      41.53447723388672,
      32.529415130615234,
      35.733428955078125,
      34.692771911621094,
      30.8265323638916,
      35.848392486572266,
      36.88600158691406,
      29.357446670532227,
      39.76295852661133,
      32.22391128540039
    ]
  },
  "timing": {
    "iteration_start_time": "2025-08-28T13:37:47.682713",
    "iteration_duration": 9.780397176742554,
    "inpainting_times": {},
    "total_inpainting_time_iteration": 0.0,
    "iteration_end_time": "2025-08-28T13:37:57.463105"
  },
  "system_state": {
    "cpu_percent_start": 0.0,
    "memory_percent_start": 9.2,
    "cpu_percent_end": 50.4,
    "memory_percent_end": 9.2
  }
}